scompose/__init__.py
scompose/version.py
scompose/client/__init__.py
scompose/client/build.py
scompose/client/check.py
scompose/client/config.py
scompose/client/create.py
scompose/client/down.py
scompose/client/exec.py
scompose/client/logs.py
scompose/client/ps.py
scompose/client/restart.py
scompose/client/run.py
scompose/client/shell.py
scompose/client/up.py
scompose/config/__init__.py
scompose/config/schema.py
scompose/logger/__init__.py
scompose/logger/message.py
scompose/logger/progress.py
scompose/project/__init__.py
scompose/project/instance.py
scompose/project/project.py
scompose/templates/__init__.py
scompose/templates/hosts
scompose/templates/resolv.conf
scompose/tests/__init__.py
scompose/tests/test_client.py
scompose/tests/test_command_args.py
scompose/tests/test_config.py
scompose/tests/test_depends_on.py
scompose/tests/test_utils.py
scompose/tests/configs/cmd_args/Singularity
scompose/tests/configs/cmd_args/singularity-compose.yml
scompose/tests/configs/config_merge/singularity-compose-1.yml
scompose/tests/configs/config_merge/singularity-compose-2.yml
scompose/tests/configs/depends_on/Singularity.first
scompose/tests/configs/depends_on/Singularity.second
scompose/tests/configs/depends_on/Singularity.third
scompose/tests/configs/depends_on/singularity-compose.yml
scompose/tests/configs/wrong_depends_on/Singularity.first
scompose/tests/configs/wrong_depends_on/Singularity.second
scompose/tests/configs/wrong_depends_on/Singularity.third
scompose/tests/configs/wrong_depends_on/singularity-compose.yml
scompose/utils/__init__.py
singularity_compose-0.1.19.dist-info/LICENSE
singularity_compose-0.1.19.dist-info/METADATA
singularity_compose-0.1.19.dist-info/WHEEL
singularity_compose-0.1.19.dist-info/entry_points.txt
singularity_compose-0.1.19.dist-info/top_level.txt
singularity_compose-0.1.19.dist-info/RECORD
