Metadata-Version: 2.1
Name: singularity-compose
Version: 0.1.19
Summary: simple orchestration for singularity containers
Home-page: http://github.com/singularityhub/singularity-compose
Author: Vanessa Sochat
Author-email: vsoch@users.noreply.github.com
Maintainer: Vanessa Sochat
Maintainer-email: vsoch@users.noreply.github.com
License: LICENSE
Keywords: singularity,compose
Classifier: Intended Audience :: Science/Research
Classifier: Intended Audience :: Developers
Classifier: License :: OSI Approved :: Mozilla Public License 2.0 (MPL 2.0)
Classifier: Programming Language :: C
Classifier: Programming Language :: Python
Classifier: Topic :: Software Development
Classifier: Topic :: Scientific/Engineering
Classifier: Operating System :: Unix
Classifier: Programming Language :: Python :: 2.7
Classifier: Programming Language :: Python :: 3
License-File: LICENSE
Requires-Dist: spython >=0.2.11
Requires-Dist: pyaml >=5.1.1
Provides-Extra: all
Requires-Dist: spython >=0.2.11 ; extra == 'all'
Requires-Dist: pyaml >=5.1.1 ; extra == 'all'
Provides-Extra: checks
Requires-Dist: spython >=0.2.11 ; extra == 'checks'
Requires-Dist: pyaml >=5.1.1 ; extra == 'checks'
Requires-Dist: jsonschema ; extra == 'checks'
